{"data_mtime":1761641018,"dep_lines":[31,34,35,36,41,95,26,27,28,29,30,31,32,37,38,40,963,17,26,32,963,2,3,4,5,6,7,8,9,10,11,12,13,14,15,16,18,20,25,1,1,1,1,1,1,1,1,1,1,1,1,1,1,1,1,1,1,1,1,1,1,1,1,1,1,1,1,1,680,23],"dep_prios":[10,5,5,5,5,5,10,5,5,5,5,20,5,5,5,5,20,5,20,20,20,10,10,10,5,10,10,10,10,10,10,10,10,10,5,5,5,5,10,5,30,30,30,30,30,30,30,30,30,30,30,30,30,30,30,30,30,30,30,30,30,30,30,30,30,30,30,30,20,10],"dependencies":["torch.fx.experimental.symbolic_shapes","torch.utils._sympy.numbers","torch.utils._sympy.symbol","torch.utils._sympy.value_ranges","torch._export.serde.schema","torch._export.serde.union","torch.export.exported_program","torch._export.non_strict_utils","torch._export.verifier","torch._subclasses.fake_tensor","torch.fx._symbolic_trace","torch.fx.experimental","torch.utils._pytree","torch.utils._traceback","torch.utils._triton","torch._export.utils","torch._inductor.ir","collections.abc","torch.export","torch.utils","torch._inductor","base64","copy","copyreg","dataclasses","heapq","inspect","io","json","keyword","logging","math","operator","traceback","typing","collections","contextlib","enum","torch","builtins","_collections_abc","_frozen_importlib","_operator","_typeshed","abc","itertools","json.decoder","json.encoder","torch._C","torch._library","torch._library.fake_class_registry","torch._ops","torch._subclasses","torch._tensor","torch.export.graph_signature","torch.fx","torch.fx.graph","torch.fx.graph_module","torch.fx.node","torch.fx.proxy","torch.nn","torch.nn.modules","torch.nn.modules.module","torch.nn.parameter","torch.utils._python_dispatch","torch.utils._sympy","torch.utils._sympy.functions","types"],"hash":"1455bb5b4e7547795ead1269b534af146c77c1ac","id":"torch._export.serde.serialize","ignore_all":true,"interface_hash":"5a1896be8f0e2e4ca98915e93ad6a74ff78e9c50","mtime":1761201539,"options":{"allow_redefinition":false,"allow_redefinition_new":false,"allow_untyped_globals":false,"always_false":[],"always_true":[],"bazel":false,"check_untyped_defs":false,"disable_bytearray_promotion":false,"disable_error_code":[],"disable_memoryview_promotion":false,"disabled_error_codes":[],"disallow_any_decorated":false,"disallow_any_explicit":false,"disallow_any_expr":false,"disallow_any_generics":false,"disallow_any_unimported":false,"disallow_incomplete_defs":false,"disallow_subclassing_any":false,"disallow_untyped_calls":false,"disallow_untyped_decorators":false,"disallow_untyped_defs":false,"enable_error_code":[],"enabled_error_codes":[],"extra_checks":false,"fixed_format_cache":false,"follow_imports":"normal","follow_imports_for_stubs":false,"follow_untyped_imports":false,"ignore_errors":false,"ignore_missing_imports":false,"implicit_optional":false,"implicit_reexport":true,"local_partial_types":false,"mypyc":false,"old_type_inference":false,"platform":"win32","plugins":[],"strict_bytes":false,"strict_concatenate":false,"strict_equality":false,"strict_equality_for_none":false,"strict_optional":true,"warn_no_return":true,"warn_return_any":false,"warn_unreachable":false,"warn_unused_ignores":false},"path":"c:\\Users\\chris\\Documents\\ai-project\\ai-project\\.venv\\Lib\\site-packages\\torch\\_export\\serde\\serialize.py","plugin_data":null,"size":155940,"suppressed":["triton.runtime.autotuner","sympy"],"version_id":"1.18.2"}